matplotgl/__init__.py
matplotgl/axes.py
matplotgl/colorbar.py
matplotgl/figure.py
matplotgl/image.py
matplotgl/line.py
matplotgl/mesh.py
matplotgl/norm.py
matplotgl/points.py
matplotgl/py.typed
matplotgl/pyplot.py
matplotgl/subplots.py
matplotgl/toolbar.py
matplotgl/utils.py
matplotgl/widgets.py
matplotgl-25.11.1.dist-info/licenses/LICENSE
matplotgl-25.11.1.dist-info/METADATA
matplotgl-25.11.1.dist-info/WHEEL
matplotgl-25.11.1.dist-info/top_level.txt
matplotgl-25.11.1.dist-info/RECORD
