Metadata-Version: 2.4
Name: matplotgl
Version: 25.11.1
Summary: Matplotlib clone for Jupyter that uses WebGL via Pythreejs
Author: Scipp contributors
License-Expression: BSD-3-Clause
Project-URL: Bug Tracker, https://github.com/scipp/matplotgl/issues
Project-URL: Documentation, https://scipp.github.io/matplotgl
Project-URL: Source, https://github.com/scipp/matplotgl
Classifier: Intended Audience :: Science/Research
Classifier: Natural Language :: English
Classifier: Operating System :: OS Independent
Classifier: Programming Language :: Python :: 3
Classifier: Programming Language :: Python :: 3 :: Only
Classifier: Programming Language :: Python :: 3.11
Classifier: Programming Language :: Python :: 3.12
Classifier: Programming Language :: Python :: 3.13
Classifier: Topic :: Scientific/Engineering
Classifier: Typing :: Typed
Requires-Python: >=3.11
License-File: LICENSE
Requires-Dist: matplotlib
Requires-Dist: pythreejs
Requires-Dist: anywidget
Provides-Extra: test
Requires-Dist: pytest; extra == "test"
Dynamic: license-file
